{
    "config": {
        "Ideal gas constant [J.K-1.mol-1]": 8.21866359283257,
        "Faraday constant [C.mol-1]": 94864.3748597796,
        "Boltzmann constant [J.K-1]": 1.6444760409560473e-23,
        "Electron charge [C]": 1.7360280520103906e-19,
        "Lithium metal partial molar volume [m3.mol-1]": 1.0872239248704368e-05,
        "Lithium plating kinetic rate constant [m.s-1]": 8.979105783219988e-10,
        "Initial plated lithium concentration [mol.m-3]": 0.0,
        "Typical plated lithium concentration [mol.m-3]": 1212.4965639960728,
        "Lithium plating transfer coefficient": 0.5094722820695005,
        "Dead lithium decay constant [s-1]": 1.5068137944536704e-06,
        "Ratio of lithium moles to SEI moles": 1.2873873627586208,
        "Inner SEI reaction proportion": 0.0,
        "Inner SEI partial molar volume [m3.mol-1]": 8.163038589384938e-05,
        "Outer SEI partial molar volume [m3.mol-1]": 9.833908900067928e-05,
        "SEI reaction exchange current density [A.m-2]": 1.703049235112715e-07,
        "SEI resistivity [Ohm.m]": 102740.32062402248,
        "Outer SEI solvent diffusivity [m2.s-1]": 4.188929835119456e-22,
        "Bulk solvent concentration [mol.m-3]": 2609.1914024480025,
        "Inner SEI open-circuit potential [V]": 0.13064000504675483,
        "Outer SEI open-circuit potential [V]": 1.0952140027166692,
        "Inner SEI electron conductivity [S.m-1]": 1.0617146469861338e-13,
        "Inner SEI lithium interstitial diffusivity [m2.s-1]": 1.3054116770206115e-20,
        "Lithium interstitial reference concentration [mol.m-3]": 14.910741698426984,
        "Initial inner SEI thickness [m]": 0.0,
        "Initial outer SEI thickness [m]": 5.151834053864385e-09,
        "EC initial concentration in electrolyte [mol.m-3]": 4364.60452701487,
        "EC diffusivity [m2.s-1]": 1.4475791333640053e-18,
        "SEI kinetic rate constant [m.s-1]": 7.582059442116042e-13,
        "SEI open-circuit potential [V]": 0.39893055589244436,
        "SEI growth activation energy [J.mol-1]": 39238.86906382462,
        "Negative electrode reaction-driven LAM factor [m3.mol-1]": 0.0,
        "Positive electrode reaction-driven LAM factor [m3.mol-1]": 0.0,
        "Negative current collector thickness [m]": 1.1030115563814675e-05,
        "Negative electrode thickness [m]": 8.759402101189175e-05,
        "Separator thickness [m]": 1.2233998538330161e-05,
        "Positive electrode thickness [m]": 9.196935213751123e-05,
        "Positive current collector thickness [m]": 1.8442070045840788e-05,
        "Electrode height [m]": 0.07211648001416253,
        "Electrode width [m]": 1.463564998598473,
        "Cell cooling surface area [m2]": 0.005997648781268685,
        "Cell volume [m3]": 2.713816809187838e-05,
        "Cell thermal expansion coefficient [m.K-1]": 9.725437731611218e-07,
        "Negative current collector conductivity [S.m-1]": 43764201.60002539,
        "Positive current collector conductivity [S.m-1]": 41829653.70453838,
        "Negative current collector density [kg.m-3]": 13723.434043417297,
        "Positive current collector density [kg.m-3]": 4034.1026039902536,
        "Negative current collector specific heat capacity [J.kg-1.K-1]": 313.46597498858176,
        "Positive current collector specific heat capacity [J.kg-1.K-1]": 980.2544866810292,
        "Negative current collector thermal conductivity [W.m-1.K-1]": 318.79346215672024,
        "Positive current collector thermal conductivity [W.m-1.K-1]": 260.64481335572236,
        "Nominal cell capacity [A.h]": 6.35685297721881,
        "Current function [A]": 5.641067111949788,
        "Contact resistance [Ohm]": 0,
        "Negative electrode conductivity [S.m-1]": 247.11143561194626,
        "Maximum concentration in negative electrode [mol.m-3]": 45001.71241099475,
        "Negative electrode porosity": 0.25830885239059703,
        "Negative electrode active material volume fraction": 0.8428889562217767,
        "Negative particle radius [m]": 6.109404805970754e-06,
        "Negative electrode Bruggeman coefficient (electrolyte)": 1.2308274023630161,
        "Negative electrode Bruggeman coefficient (electrode)": 2.0438540563252596,
        "Negative electrode charge transfer coefficient": 0.5567306086489092,
        "Negative electrode double-layer capacity [F.m-2]": 0.28452832762629887,
        "Negative electrode density [kg.m-3]": 1831.5197858085912,
        "Negative electrode specific heat capacity [J.kg-1.K-1]": 688.2674790836428,
        "Negative electrode thermal conductivity [W.m-1.K-1]": 2.5329887359661756,
        "Negative electrode OCP entropic change [V.K-1]": 0.0,
        "Negative electrode Poisson's ratio": 0.3188988158195548,
        "Negative electrode Young's modulus [Pa]": 14596418269.405853,
        "Negative electrode reference concentration for free of deformation [mol.m-3]": 0.0,
        "Negative electrode partial molar volume [m3.mol-1]": 2.8006754676892716e-06,
        "Negative electrode initial crack length [m]": 1.5356320615333852e-08,
        "Negative electrode initial crack width [m]": 2.4960168089371817e-08,
        "Negative electrode number of cracks per unit area [m-2]": 2895601102445187.5,
        "Negative electrode Paris' law constant b": 0.7506153745895494,
        "Negative electrode Paris' law constant m": 2.168480434947998,
        "Negative electrode LAM constant proportional term [s-1]": 2.635848593504571e-07,
        "Negative electrode LAM constant exponential term": 2.9880485925706495,
        "Negative electrode critical stress [Pa]": 71875846.21029061,
        "Positive electrode conductivity [S.m-1]": 0.24203243866461985,
        "Maximum concentration in positive electrode [mol.m-3]": 66616.25902841608,
        "Positive electrode porosity": 0.5353109442671959,
        "Positive electrode active material volume fraction": 0.8941096422804076,
        "Positive particle radius [m]": 7.3740409017147875e-06,
        "Positive electrode Bruggeman coefficient (electrolyte)": 1.2559765546878516,
        "Positive electrode Bruggeman coefficient (electrode)": 2.0271475042979543,
        "Positive electrode charge transfer coefficient": 0.365189259765827,
        "Positive electrode double-layer capacity [F.m-2]": 0.10019155639982452,
        "Positive electrode density [kg.m-3]": 3292.2067290019545,
        "Positive electrode specific heat capacity [J.kg-1.K-1]": 926.435057987037,
        "Positive electrode thermal conductivity [W.m-1.K-1]": 2.48623533464997,
        "Positive electrode OCP entropic change [V.K-1]": 0.0,
        "Positive electrode Poisson's ratio": 0.24759911517807523,
        "Positive electrode Young's modulus [Pa]": 405360357708.56213,
        "Positive electrode reference concentration for free of deformation [mol.m-3]": 0.0,
        "Positive electrode partial molar volume [m3.mol-1]": 1.2607862937541126e-05,
        "Positive electrode initial crack length [m]": 1.6996238007355768e-08,
        "Positive electrode initial crack width [m]": 1.7759020345491945e-08,
        "Positive electrode number of cracks per unit area [m-2]": 3143194637325211.0,
        "Positive electrode Paris' law constant b": 1.0776714460238934,
        "Positive electrode Paris' law constant m": 2.376262216789848,
        "Positive electrode LAM constant proportional term [s-1]": 4.435214103004482e-07,
        "Positive electrode LAM constant exponential term": 2.4043004808377204,
        "Positive electrode critical stress [Pa]": 298900945.12322026,
        "Separator porosity": 0.5278847136330113,
        "Separator Bruggeman coefficient (electrolyte)": 1.0781303261940471,
        "Separator density [kg.m-3]": 438.35989066900544,
        "Separator specific heat capacity [J.kg-1.K-1]": 961.4288735829878,
        "Separator thermal conductivity [W.m-1.K-1]": 0.22733059126491628,
        "Initial concentration in electrolyte [mol.m-3]": 1093.5722880965727,
        "Cation transference number": 0.24474663748069864,
        "Thermodynamic factor": 0.7677993054841518,
        "Reference temperature [K]": 259.7233864722153,
        "Total heat transfer coefficient [W.m-2.K-1]": 11.790632058757602,
        "Ambient temperature [K]": 272.5697505660605,
        "Number of electrodes connected in parallel to make a cell": 1.1265795899233975,
        "Number of cells connected in series to make a battery": 0.951747780294183,
        "Lower voltage cut-off [V]": 2.706997569745235,
        "Upper voltage cut-off [V]": 5.480530179500163,
        "Open-circuit voltage at 0% SOC [V]": 1.8243079428503337,
        "Open-circuit voltage at 100% SOC [V]": 4.586681904717486,
        "Initial concentration in negative electrode [mol.m-3]": 36593.39547107605,
        "Initial concentration in positive electrode [mol.m-3]": 15751.324073233947,
        "Initial temperature [K]": 280.61575068366744
    },
    "V": [
        4.1146061723664396,
        4.022079934186186,
        3.9637651792982167,
        3.9326820724556413,
        3.9178884522976576,
        3.911492987646601,
        3.9068548410406603,
        3.9018464694833606,
        3.8954388225526264,
        3.8874457204984743,
        3.8780740769552366,
        3.8677068046871326,
        3.8565609415261006,
        3.84537115649497,
        3.8345039977471744,
        3.8236125250099082,
        3.8132093866028525,
        3.80341988644047,
        3.793654744694638,
        3.784474673667684,
        3.7754701303929563,
        3.7665709467184234,
        3.7579127471126728,
        3.749225952951201,
        3.7407700215140878,
        3.7321429622036844,
        3.724124946760159,
        3.7158171490023353,
        3.707797559894654,
        3.699947258829554,
        3.6921488541200227,
        3.6849047663772683,
        3.6772011362839336,
        3.669604283828109,
        3.661582468518464,
        3.6542483485360924,
        3.6465452309815727,
        3.638854210122952,
        3.631207723718393,
        3.6233374296924037,
        3.6158116288723816,
        3.608304533689058,
        3.6012140164758453,
        3.5940856904520437,
        3.586364113687331,
        3.5792161642604086,
        3.572140663190095,
        3.5645439320664183,
        3.558007536615875,
        3.5508767647043187,
        3.544243139713755,
        3.5378352168733707,
        3.531479178328782,
        3.525512369447217,
        3.5193901208515275,
        3.5138880902699223,
        3.508141823580159,
        3.503016477307317,
        3.4973520784551804,
        3.4926264590751464,
        3.4870439054355176,
        3.482612005722247,
        3.477130186651937,
        3.472915543927437,
        3.4676241713473743,
        3.463179550063242,
        3.458161025057131,
        3.4537080390090216,
        3.448795042507243,
        3.444262568853391,
        3.439501944936997,
        3.434986069403842,
        3.4303101616492393,
        3.425688769181855,
        3.4208175170927433,
        3.4162153425285147,
        3.411307357798149,
        3.406749867531561,
        3.4015663620182313,
        3.3966827855518558,
        3.3912841947365058,
        3.3863643525352987,
        3.3811795131365994,
        3.376022074586232,
        3.369991223118027,
        3.3648062971319286,
        3.3589699691777124,
        3.3531006854703493,
        3.347016413317534,
        3.340727572225574,
        3.3345697110445913,
        3.3282910827557664,
        3.321793825293598,
        3.315719417115659,
        3.309648538933394,
        3.3035063271355187,
        3.2974944881020303,
        3.2914251415318283,
        3.2852281617443255,
        3.279075591519483
    ],
    "time": [
        0.0,
        36.36363636363637,
        72.72727272727273,
        109.0909090909091,
        145.45454545454547,
        181.81818181818184,
        218.1818181818182,
        254.54545454545456,
        290.90909090909093,
        327.2727272727273,
        363.6363636363637,
        400.00000000000006,
        436.3636363636364,
        472.72727272727275,
        509.0909090909091,
        545.4545454545455,
        581.8181818181819,
        618.1818181818182,
        654.5454545454546,
        690.909090909091,
        727.2727272727274,
        763.6363636363637,
        800.0000000000001,
        836.3636363636365,
        872.7272727272727,
        909.0909090909091,
        945.4545454545455,
        981.8181818181819,
        1018.1818181818182,
        1054.5454545454547,
        1090.909090909091,
        1127.2727272727275,
        1163.6363636363637,
        1200.0,
        1236.3636363636365,
        1272.7272727272727,
        1309.0909090909092,
        1345.4545454545455,
        1381.818181818182,
        1418.1818181818182,
        1454.5454545454547,
        1490.909090909091,
        1527.2727272727275,
        1563.6363636363637,
        1600.0000000000002,
        1636.3636363636365,
        1672.727272727273,
        1709.0909090909092,
        1745.4545454545455,
        1781.818181818182,
        1818.1818181818182,
        1854.5454545454547,
        1890.909090909091,
        1927.2727272727275,
        1963.6363636363637,
        2000.0000000000002,
        2036.3636363636365,
        2072.727272727273,
        2109.0909090909095,
        2145.4545454545455,
        2181.818181818182,
        2218.1818181818185,
        2254.545454545455,
        2290.909090909091,
        2327.2727272727275,
        2363.636363636364,
        2400.0,
        2436.3636363636365,
        2472.727272727273,
        2509.0909090909095,
        2545.4545454545455,
        2581.818181818182,
        2618.1818181818185,
        2654.545454545455,
        2690.909090909091,
        2727.2727272727275,
        2763.636363636364,
        2800.0000000000005,
        2836.3636363636365,
        2872.727272727273,
        2909.0909090909095,
        2945.4545454545455,
        2981.818181818182,
        3018.1818181818185,
        3054.545454545455,
        3090.909090909091,
        3127.2727272727275,
        3163.636363636364,
        3200.0000000000005,
        3236.3636363636365,
        3272.727272727273,
        3309.0909090909095,
        3345.454545454546,
        3381.818181818182,
        3418.1818181818185,
        3454.545454545455,
        3490.909090909091,
        3527.2727272727275,
        3563.636363636364,
        3600.0
    ]
}