{
    "config": {
        "Ideal gas constant [J.K-1.mol-1]": 8.540440150752357,
        "Faraday constant [C.mol-1]": 117399.30236285781,
        "Boltzmann constant [J.K-1]": 1.1900894689871391e-23,
        "Electron charge [C]": 1.4348070125631818e-19,
        "Ratio of lithium moles to SEI moles": 1.5798866469265593,
        "Inner SEI reaction proportion": 0.5081132978830183,
        "Inner SEI partial molar volume [m3.mol-1]": 0.00010666310864438608,
        "Outer SEI partial molar volume [m3.mol-1]": 9.230099210072477e-05,
        "SEI reaction exchange current density [A.m-2]": 1.313932122775538e-07,
        "SEI resistivity [Ohm.m]": 174984.8709726849,
        "Outer SEI solvent diffusivity [m2.s-1]": 2.9407672478777137e-22,
        "Bulk solvent concentration [mol.m-3]": 3152.9993440315993,
        "Inner SEI open-circuit potential [V]": 0.09876023296021022,
        "Outer SEI open-circuit potential [V]": 0.6545849826742208,
        "Inner SEI electron conductivity [S.m-1]": 1.3203427178969623e-13,
        "Inner SEI lithium interstitial diffusivity [m2.s-1]": 1.0008205312492466e-20,
        "Lithium interstitial reference concentration [mol.m-3]": 13.804797367460957,
        "Initial inner SEI thickness [m]": 3.072661533863909e-09,
        "Initial outer SEI thickness [m]": 3.048072604538866e-09,
        "EC initial concentration in electrolyte [mol.m-3]": 5149.027020835572,
        "EC diffusivity [m2.s-1]": 1.8317302803651324e-18,
        "SEI kinetic rate constant [m.s-1]": 1.1144397194639373e-12,
        "SEI open-circuit potential [V]": 0.41073236675012564,
        "SEI growth activation energy [J.mol-1]": 0.0,
        "Negative electrode reaction-driven LAM factor [m3.mol-1]": 0.0,
        "Positive electrode reaction-driven LAM factor [m3.mol-1]": 0.0,
        "Negative current collector thickness [m]": 8.790448017070681e-06,
        "Negative electrode thickness [m]": 5.842929603894437e-05,
        "Separator thickness [m]": 2.36805631038078e-05,
        "Positive electrode thickness [m]": 6.051983044674006e-05,
        "Positive current collector thickness [m]": 1.1415076712111423e-05,
        "Electrode height [m]": 0.19357170575945082,
        "Electrode width [m]": 0.1260138866829752,
        "Negative tab width [m]": 0.04419745488997686,
        "Negative tab centre y-coordinate [m]": 0.013257130015532841,
        "Negative tab centre z-coordinate [m]": 0.16483020815031285,
        "Positive tab width [m]": 0.049543518923870974,
        "Positive tab centre y-coordinate [m]": 0.16845901620831094,
        "Positive tab centre z-coordinate [m]": 0.2106320768292087,
        "Cell cooling surface area [m2]": 0.03994364000683982,
        "Cell volume [m3]": 4.925605986596451e-06,
        "Negative current collector conductivity [S.m-1]": 72730291.53283778,
        "Positive current collector conductivity [S.m-1]": 43432584.65978048,
        "Negative current collector density [kg.m-3]": 14029.15535223709,
        "Positive current collector density [kg.m-3]": 3306.777850343201,
        "Negative current collector specific heat capacity [J.kg-1.K-1]": 349.34086491528416,
        "Positive current collector specific heat capacity [J.kg-1.K-1]": 925.0763610756117,
        "Negative current collector thermal conductivity [W.m-1.K-1]": 315.98018710594283,
        "Positive current collector thermal conductivity [W.m-1.K-1]": 143.1963884064921,
        "Nominal cell capacity [A.h]": 0.3296734878880802,
        "Current function [A]": 0.5264110989937016,
        "Contact resistance [Ohm]": 0,
        "Negative electrode conductivity [S.m-1]": 85.54681364695728,
        "Maximum concentration in negative electrode [mol.m-3]": 28908.08382214983,
        "Negative electrode porosity": 0.4874442461514575,
        "Negative electrode active material volume fraction": 0.4004531907836724,
        "Negative particle radius [m]": 5.461159361822225e-07,
        "Negative electrode Bruggeman coefficient (electrolyte)": 2.2332570201080095,
        "Negative electrode Bruggeman coefficient (electrode)": 1.7876144736989106,
        "Negative electrode charge transfer coefficient": 0.5294852997569738,
        "Negative electrode double-layer capacity [F.m-2]": 0.16173649461745715,
        "Negative electrode density [kg.m-3]": 2012.5476988742469,
        "Negative electrode specific heat capacity [J.kg-1.K-1]": 809.1670829292577,
        "Negative electrode thermal conductivity [W.m-1.K-1]": 1.1229760340800992,
        "Negative electrode OCP entropic change [V.K-1]": 0.0,
        "Positive electrode conductivity [S.m-1]": 8.736092726160514,
        "Maximum concentration in positive electrode [mol.m-3]": 44406.2997151706,
        "Positive electrode porosity": 0.3179958263440828,
        "Positive electrode active material volume fraction": 0.4482061249496251,
        "Positive particle radius [m]": 1.66323501024855e-06,
        "Positive electrode Bruggeman coefficient (electrolyte)": 1.697970432208154,
        "Positive electrode Bruggeman coefficient (electrode)": 1.6596018102580852,
        "Positive electrode charge transfer coefficient": 0.4925577437655527,
        "Positive electrode double-layer capacity [F.m-2]": 0.2082791383875485,
        "Positive electrode density [kg.m-3]": 4547.94404479257,
        "Positive electrode specific heat capacity [J.kg-1.K-1]": 737.1324285012215,
        "Positive electrode thermal conductivity [W.m-1.K-1]": 1.7229715223032323,
        "Positive electrode OCP entropic change [V.K-1]": 0.0,
        "Separator porosity": 0.44058395033848735,
        "Separator Bruggeman coefficient (electrolyte)": 1.4886660342807911,
        "Separator density [kg.m-3]": 540.0378940940134,
        "Separator specific heat capacity [J.kg-1.K-1]": 577.6414202137798,
        "Separator thermal conductivity [W.m-1.K-1]": 0.09904133006508281,
        "Initial concentration in electrolyte [mol.m-3]": 1309.3419831405415,
        "Cation transference number": 0.3800474667270021,
        "Thermodynamic factor": 0.7174630593454656,
        "Reference temperature [K]": 328.09734738848846,
        "Negative current collector surface heat transfer coefficient [W.m-2.K-1]": 0.0,
        "Positive current collector surface heat transfer coefficient [W.m-2.K-1]": 0.0,
        "Negative tab heat transfer coefficient [W.m-2.K-1]": 15.419963718096737,
        "Positive tab heat transfer coefficient [W.m-2.K-1]": 19.37201035545231,
        "Edge heat transfer coefficient [W.m-2.K-1]": 0.3290991340593802,
        "Total heat transfer coefficient [W.m-2.K-1]": 21.66566276889607,
        "Ambient temperature [K]": 242.8914389812598,
        "Number of electrodes connected in parallel to make a cell": 1.1975382554900558,
        "Number of cells connected in series to make a battery": 1.275311306838602,
        "Lower voltage cut-off [V]": 2.9125980909435087,
        "Upper voltage cut-off [V]": 4.196685521460699,
        "Open-circuit voltage at 0% SOC [V]": 3.667544015514137,
        "Open-circuit voltage at 100% SOC [V]": 4.270455861005046,
        "Initial concentration in negative electrode [mol.m-3]": 15709.772760683192,
        "Initial concentration in positive electrode [mol.m-3]": 17442.894788051493,
        "Initial temperature [K]": 310.4296035617767
    },
    "V": [
        4.047773240343148,
        4.001048327792452,
        3.9737170736380123,
        3.9503322261775122,
        3.9288237832736295,
        3.9085507090551275,
        3.8890600902019927,
        3.8697117052126995,
        3.850041016354025,
        3.8299150785300644,
        3.8092593928803553,
        3.7875540844253597,
        3.7636624963522336,
        3.7364205579166394,
        3.7057190443201202,
        3.672793885842026,
        3.637579038977114,
        3.600850279925389,
        3.5628769504874795,
        3.5231282463543563,
        3.4834618749751933,
        3.4429532015846416,
        3.398011285759355,
        3.345280441540262,
        3.2822350952985424,
        3.209542988800047,
        3.125782146506984,
        3.0855245568628327,
        3.0691622771701788,
        3.046491685596897,
        3.0226293067850474,
        2.977640133727598,
        2.9126080909435066
    ],
    "time": [
        0.0,
        36.36363636363637,
        72.72727272727273,
        109.0909090909091,
        145.45454545454547,
        181.81818181818184,
        218.1818181818182,
        254.54545454545456,
        290.90909090909093,
        327.2727272727273,
        363.6363636363637,
        400.00000000000006,
        436.3636363636364,
        472.72727272727275,
        509.0909090909091,
        545.4545454545455,
        581.8181818181819,
        618.1818181818182,
        654.5454545454546,
        690.909090909091,
        727.2727272727274,
        763.6363636363637,
        800.0000000000001,
        836.3636363636365,
        872.7272727272727,
        909.0909090909091,
        945.4545454545455,
        954.8295454545455,
        957.1732954545455,
        959.5170454545455,
        961.8607954545455,
        964.2045454545455,
        966.2558215131836
    ]
}