{
    "config": {
        "Ideal gas constant [J.K-1.mol-1]": 6.87930478962483,
        "Faraday constant [C.mol-1]": 110709.64788405538,
        "Boltzmann constant [J.K-1]": 1.930595848079823e-23,
        "Electron charge [C]": 1.0808378774941881e-19,
        "Lithium metal partial molar volume [m3.mol-1]": 1.0752916885319386e-05,
        "Lithium plating kinetic rate constant [m.s-1]": 7.460662355454979e-10,
        "Initial plated lithium concentration [mol.m-3]": 0.0,
        "Typical plated lithium concentration [mol.m-3]": 1263.5000250425087,
        "Lithium plating transfer coefficient": 0.8655759140541985,
        "Dead lithium decay constant [s-1]": 6.636560911722483e-07,
        "Ratio of lithium moles to SEI moles": 0.8600543063509554,
        "Inner SEI reaction proportion": 0.0,
        "Inner SEI partial molar volume [m3.mol-1]": 0.00010331978298353352,
        "Outer SEI partial molar volume [m3.mol-1]": 8.615077824117137e-05,
        "SEI reaction exchange current density [A.m-2]": 1.8917282494141986e-07,
        "SEI resistivity [Ohm.m]": 210072.46128048227,
        "Outer SEI solvent diffusivity [m2.s-1]": 2.4696591671015835e-22,
        "Bulk solvent concentration [mol.m-3]": 1964.822241101937,
        "Inner SEI open-circuit potential [V]": 0.07050294413974323,
        "Outer SEI open-circuit potential [V]": 0.40886934053684176,
        "Inner SEI electron conductivity [S.m-1]": 8.162467914083306e-14,
        "Inner SEI lithium interstitial diffusivity [m2.s-1]": 1.186627601911191e-20,
        "Lithium interstitial reference concentration [mol.m-3]": 24.199255472597827,
        "Initial inner SEI thickness [m]": 0.0,
        "Initial outer SEI thickness [m]": 5.341235064108536e-09,
        "EC initial concentration in electrolyte [mol.m-3]": 4684.851974412282,
        "EC diffusivity [m2.s-1]": 1.4714237590830686e-18,
        "SEI kinetic rate constant [m.s-1]": 6.949935981612896e-13,
        "SEI open-circuit potential [V]": 0.2809351329471639,
        "SEI growth activation energy [J.mol-1]": 44105.11660615599,
        "Negative electrode reaction-driven LAM factor [m3.mol-1]": 0.0,
        "Positive electrode reaction-driven LAM factor [m3.mol-1]": 0.0,
        "Negative current collector thickness [m]": 1.0860081383571653e-05,
        "Negative electrode thickness [m]": 9.744389482532545e-05,
        "Separator thickness [m]": 1.352676548463071e-05,
        "Positive electrode thickness [m]": 8.67840181173562e-05,
        "Positive current collector thickness [m]": 1.2604841067329796e-05,
        "Electrode height [m]": 0.08193153737424547,
        "Electrode width [m]": 1.5982940786625315,
        "Cell cooling surface area [m2]": 0.0062271123611322,
        "Cell volume [m3]": 2.5835231791778235e-05,
        "Cell thermal expansion coefficient [m.K-1]": 6.794170873465888e-07,
        "Negative current collector conductivity [S.m-1]": 92297456.49773943,
        "Positive current collector conductivity [S.m-1]": 23527584.12304566,
        "Negative current collector density [kg.m-3]": 8109.777935209656,
        "Positive current collector density [kg.m-3]": 2419.6226050002156,
        "Negative current collector specific heat capacity [J.kg-1.K-1]": 395.48665148990193,
        "Positive current collector specific heat capacity [J.kg-1.K-1]": 900.6349591948924,
        "Negative current collector thermal conductivity [W.m-1.K-1]": 430.2564965372112,
        "Positive current collector thermal conductivity [W.m-1.K-1]": 303.37727030994796,
        "Nominal cell capacity [A.h]": 3.6860264388134194,
        "Current function [A]": 4.138195740803469,
        "Contact resistance [Ohm]": 0,
        "Negative electrode conductivity [S.m-1]": 95.35219996253207,
        "Maximum concentration in negative electrode [mol.m-3]": 39297.87862378539,
        "Negative electrode porosity": 0.21280203699751454,
        "Negative electrode active material volume fraction": 0.6511632063172796,
        "Negative particle radius [m]": 5.017039898208807e-06,
        "Negative electrode Bruggeman coefficient (electrolyte)": 1.2692718242078345,
        "Negative electrode Bruggeman coefficient (electrode)": 1.3515940680524499,
        "Negative electrode charge transfer coefficient": 0.6101464383618429,
        "Negative electrode double-layer capacity [F.m-2]": 0.22410219466395068,
        "Negative electrode density [kg.m-3]": 1685.3407815603616,
        "Negative electrode specific heat capacity [J.kg-1.K-1]": 788.9969853285775,
        "Negative electrode thermal conductivity [W.m-1.K-1]": 2.2734812856638444,
        "Negative electrode OCP entropic change [V.K-1]": 0.0,
        "Negative electrode Poisson's ratio": 0.30852350077452967,
        "Negative electrode Young's modulus [Pa]": 11982400073.343456,
        "Negative electrode reference concentration for free of deformation [mol.m-3]": 0.0,
        "Negative electrode partial molar volume [m3.mol-1]": 2.856992936278181e-06,
        "Negative electrode initial crack length [m]": 2.451538448727128e-08,
        "Negative electrode initial crack width [m]": 1.3133244783038246e-08,
        "Negative electrode number of cracks per unit area [m-2]": 4437269273923582.0,
        "Negative electrode Paris' law constant b": 0.9611117377284493,
        "Negative electrode Paris' law constant m": 1.6565783335325284,
        "Negative electrode LAM constant proportional term [s-1]": 3.322668787210303e-07,
        "Negative electrode LAM constant exponential term": 2.1415158770267864,
        "Negative electrode critical stress [Pa]": 70309005.96755284,
        "Positive electrode conductivity [S.m-1]": 0.13590439557660974,
        "Maximum concentration in positive electrode [mol.m-3]": 60467.600009913884,
        "Positive electrode porosity": 0.4171497193623275,
        "Positive electrode active material volume fraction": 0.6344599031485987,
        "Positive particle radius [m]": 3.313085814675004e-06,
        "Positive electrode Bruggeman coefficient (electrolyte)": 1.196983566389648,
        "Positive electrode Bruggeman coefficient (electrode)": 1.2530754114404965,
        "Positive electrode charge transfer coefficient": 0.3364193111583683,
        "Positive electrode double-layer capacity [F.m-2]": 0.11382290564692203,
        "Positive electrode density [kg.m-3]": 2116.326344466841,
        "Positive electrode specific heat capacity [J.kg-1.K-1]": 960.9970962317773,
        "Positive electrode thermal conductivity [W.m-1.K-1]": 2.3499789009205814,
        "Positive electrode OCP entropic change [V.K-1]": 0.0,
        "Positive electrode Poisson's ratio": 0.18501306163519032,
        "Positive electrode Young's modulus [Pa]": 117990434092.5597,
        "Positive electrode reference concentration for free of deformation [mol.m-3]": 0.0,
        "Positive electrode partial molar volume [m3.mol-1]": 1.2080079424601014e-05,
        "Positive electrode initial crack length [m]": 1.7982140169510007e-08,
        "Positive electrode initial crack width [m]": 1.6826881414780653e-08,
        "Positive electrode number of cracks per unit area [m-2]": 2159979357302758.0,
        "Positive electrode Paris' law constant b": 1.0197390897576033,
        "Positive electrode Paris' law constant m": 1.2700435934793997,
        "Positive electrode LAM constant proportional term [s-1]": 1.8380727376622713e-07,
        "Positive electrode LAM constant exponential term": 1.4934488156342915,
        "Positive electrode critical stress [Pa]": 343266173.80025506,
        "Separator porosity": 0.41020499875866867,
        "Separator Bruggeman coefficient (electrolyte)": 1.7277118904682849,
        "Separator density [kg.m-3]": 305.5444709133186,
        "Separator specific heat capacity [J.kg-1.K-1]": 540.6961811294254,
        "Separator thermal conductivity [W.m-1.K-1]": 0.13171713198880924,
        "Initial concentration in electrolyte [mol.m-3]": 889.1786379617041,
        "Cation transference number": 0.22025182527431852,
        "Thermodynamic factor": 1.1814208822408645,
        "Reference temperature [K]": 273.8167643841186,
        "Total heat transfer coefficient [W.m-2.K-1]": 9.684789617367876,
        "Ambient temperature [K]": 375.13642860751264,
        "Number of electrodes connected in parallel to make a cell": 0.5045243900333165,
        "Number of cells connected in series to make a battery": 0.8448003327920233,
        "Lower voltage cut-off [V]": 2.028750960132724,
        "Upper voltage cut-off [V]": 5.341227195031305,
        "Open-circuit voltage at 0% SOC [V]": 2.7612467536253416,
        "Open-circuit voltage at 100% SOC [V]": 3.692037412976661,
        "Initial concentration in negative electrode [mol.m-3]": 29480.089340391627,
        "Initial concentration in positive electrode [mol.m-3]": 19243.424159620663,
        "Initial temperature [K]": 269.91939057500974
    },
    "V": [
        4.071044115876484,
        4.0541864972195105,
        4.04883169996854,
        4.043126127597309,
        4.037299969565849,
        4.031078807934067,
        4.023806710609636,
        4.01575736156299,
        4.007022905797763,
        3.9968548403196666,
        3.9859040797160787,
        3.974680350302135,
        3.9626255743276713,
        3.9510747257561327,
        3.9391553140067392,
        3.926867250008476,
        3.9147254961386655,
        3.9013165406029877,
        3.888142641863933,
        3.875630076904259,
        3.8650717586555494,
        3.8562580140813285,
        3.8476416825218496,
        3.839563375420453,
        3.831541049116944,
        3.8238918407882583,
        3.8160071942350937,
        3.808268064049437,
        3.800263223042544,
        3.7920513164995797,
        3.783806657275127,
        3.7751406537993146,
        3.7661773428755074,
        3.75643933310043,
        3.746631818992535,
        3.7366586586387607,
        3.7257372093452794,
        3.7148655088860867,
        3.7043295129002543,
        3.6935275725215475,
        3.6829536020515867,
        3.672733304029033,
        3.6627666942808403,
        3.653073160347753,
        3.6436369267770163,
        3.6345951950313253,
        3.626084704792993,
        3.6175162410585586,
        3.6092774050206495,
        3.601250702630299,
        3.5929650640780615,
        3.5846537635677502,
        3.5762784014784827,
        3.567738749588335,
        3.5587626533665833,
        3.549757625316612,
        3.5401954970717107,
        3.5302409117506084,
        3.5196028421663854,
        3.508317153289056,
        3.496978288828511,
        3.4847756317143777,
        3.4723173373939606,
        3.4622854988448295,
        3.454606949362817,
        3.448394132461586,
        3.441704980957747,
        3.434206618581482,
        3.4262220569112234,
        3.4170742103527387,
        3.4066044626064125,
        3.3928091722135894,
        3.3753556408770007,
        3.3560978016839567,
        3.33036942226503,
        3.301731784228704,
        3.273531216644037,
        3.2438200200436587,
        3.2066474481720357,
        3.176194861853927,
        3.1369757539184993,
        3.1077180002882066,
        3.063651807230248,
        3.0192194499468945,
        2.950716259685052,
        2.8575663216264346,
        2.6783949468010255,
        2.4633671938642574,
        2.2718749444282267,
        2.0806412243471,
        2.028760960132722
    ],
    "time": [
        0.0,
        36.36363636363637,
        72.72727272727273,
        109.0909090909091,
        145.45454545454547,
        181.81818181818184,
        218.1818181818182,
        254.54545454545456,
        290.90909090909093,
        327.2727272727273,
        363.6363636363637,
        400.00000000000006,
        436.3636363636364,
        472.72727272727275,
        509.0909090909091,
        545.4545454545455,
        581.8181818181819,
        618.1818181818182,
        654.5454545454546,
        690.909090909091,
        727.2727272727274,
        763.6363636363637,
        800.0000000000001,
        836.3636363636365,
        872.7272727272727,
        909.0909090909091,
        945.4545454545455,
        981.8181818181819,
        1018.1818181818182,
        1054.5454545454547,
        1090.909090909091,
        1127.2727272727275,
        1163.6363636363637,
        1200.0,
        1236.3636363636365,
        1272.7272727272727,
        1309.0909090909092,
        1345.4545454545455,
        1381.818181818182,
        1418.1818181818182,
        1454.5454545454547,
        1490.909090909091,
        1527.2727272727275,
        1563.6363636363637,
        1600.0000000000002,
        1636.3636363636365,
        1672.727272727273,
        1709.0909090909092,
        1745.4545454545455,
        1781.818181818182,
        1818.1818181818182,
        1854.5454545454547,
        1890.909090909091,
        1927.2727272727275,
        1963.6363636363637,
        2000.0000000000002,
        2036.3636363636365,
        2072.727272727273,
        2109.0909090909095,
        2145.4545454545455,
        2181.818181818182,
        2218.1818181818185,
        2254.545454545455,
        2290.909090909091,
        2327.2727272727275,
        2363.636363636364,
        2400.0,
        2436.3636363636365,
        2472.727272727273,
        2509.0909090909095,
        2545.4545454545455,
        2581.818181818182,
        2618.1818181818185,
        2654.545454545455,
        2690.909090909091,
        2727.2727272727275,
        2763.636363636364,
        2800.0000000000005,
        2836.3636363636365,
        2872.727272727273,
        2909.0909090909095,
        2945.4545454545455,
        2981.818181818182,
        3018.1818181818185,
        3054.545454545455,
        3090.909090909091,
        3127.2727272727275,
        3163.636363636364,
        3200.0000000000005,
        3236.3636363636365,
        3245.843980580664
    ]
}